[{
        "id": 1,
        "first_name": "Germain",
        "last_name": "Troup",
        "email": "gtroup0@xing.com",
        "gender": "Polygender"
    },
    {
        "id": 2,
        "first_name": "Nertie",
        "last_name": "Sweedland",
        "email": "nsweedland1@last.fm",
        "gender": "Polygender"
    },
    {
        "id": 3,
        "first_name": "Stevie",
        "last_name": "Bowden",
        "email": "sbowden2@over-blog.com",
        "gender": "Polygender"
    },
    {
        "id": 4,
        "first_name": "Doris",
        "last_name": "Amort",
        "email": "damort3@sourceforge.net",
        "gender": "Genderqueer"
    },
    {
        "id": 5,
        "first_name": "Quinn",
        "last_name": "Bickley",
        "email": "qbickley4@wikispaces.com",
        "gender": "Non-binary"
    },
    {
        "id": 6,
        "first_name": "Almeda",
        "last_name": "Bakes",
        "email": "abakes5@craigslist.org",
        "gender": "Male"
    },
    {
        "id": 7,
        "first_name": "Kaila",
        "last_name": "Heartfield",
        "email": "kheartfield6@china.com.cn",
        "gender": "Non-binary"
    },
    {
        "id": 8,
        "first_name": "Bobbette",
        "last_name": "Greensall",
        "email": "bgreensall7@shareasale.com",
        "gender": "Male"
    },
    {
        "id": 9,
        "first_name": "Rosetta",
        "last_name": "Cottill",
        "email": "rcottill8@dropbox.com",
        "gender": "Polygender"
    },
    {
        "id": 10,
        "first_name": "Gallard",
        "last_name": "Scotney",
        "email": "gscotney9@surveymonkey.com",
        "gender": "Non-binary"
    },
    {
        "id": 11,
        "first_name": "Ofelia",
        "last_name": "Rosi",
        "email": "orosia@china.com.cn",
        "gender": "Agender"
    },
    {
        "id": 12,
        "first_name": "Terrence",
        "last_name": "Fairney",
        "email": "tfairneyb@devhub.com",
        "gender": "Polygender"
    },
    {
        "id": 13,
        "first_name": "Leela",
        "last_name": "Speenden",
        "email": "lspeendenc@dion.ne.jp",
        "gender": "Non-binary"
    },
    {
        "id": 14,
        "first_name": "Arlena",
        "last_name": "Pudan",
        "email": "apudand@multiply.com",
        "gender": "Genderqueer"
    },
    {
        "id": 15,
        "first_name": "Yanaton",
        "last_name": "Jamison",
        "email": "yjamisone@ebay.com",
        "gender": "Non-binary"
    },
    {
        "id": 16,
        "first_name": "Camila",
        "last_name": "Arnaud",
        "email": "carnaudf@latimes.com",
        "gender": "Bigender"
    },
    {
        "id": 17,
        "first_name": "Bryna",
        "last_name": "Pennington",
        "email": "bpenningtong@typepad.com",
        "gender": "Female"
    },
    {
        "id": 18,
        "first_name": "Euphemia",
        "last_name": "Lage",
        "email": "elageh@bloglovin.com",
        "gender": "Genderqueer"
    },
    {
        "id": 19,
        "first_name": "Zsazsa",
        "last_name": "Whalebelly",
        "email": "zwhalebellyi@google.co.uk",
        "gender": "Agender"
    },
    {
        "id": 20,
        "first_name": "Renie",
        "last_name": "Giraudat",
        "email": "rgiraudatj@biblegateway.com",
        "gender": "Polygender"
    },
    {
        "id": 21,
        "first_name": "Dimitri",
        "last_name": "Willetts",
        "email": "dwillettsk@oracle.com",
        "gender": "Non-binary"
    },
    {
        "id": 22,
        "first_name": "Angus",
        "last_name": "Gibson",
        "email": "agibsonl@china.com.cn",
        "gender": "Polygender"
    },
    {
        "id": 23,
        "first_name": "Jud",
        "last_name": "Myall",
        "email": "jmyallm@google.fr",
        "gender": "Polygender"
    },
    {
        "id": 24,
        "first_name": "Katine",
        "last_name": "Ghirigori",
        "email": "kghirigorin@biblegateway.com",
        "gender": "Genderfluid"
    },
    {
        "id": 25,
        "first_name": "Tomaso",
        "last_name": "Matantsev",
        "email": "tmatantsevo@wiley.com",
        "gender": "Non-binary"
    },
    {
        "id": 26,
        "first_name": "Ilka",
        "last_name": "Theaker",
        "email": "itheakerp@amazon.co.uk",
        "gender": "Female"
    },
    {
        "id": 27,
        "first_name": "Minnie",
        "last_name": "Unwins",
        "email": "munwinsq@aboutads.info",
        "gender": "Genderqueer"
    },
    {
        "id": 28,
        "first_name": "Rosie",
        "last_name": "Jupp",
        "email": "rjuppr@pen.io",
        "gender": "Agender"
    },
    {
        "id": 29,
        "first_name": "Fifine",
        "last_name": "Bissell",
        "email": "fbissells@opera.com",
        "gender": "Genderqueer"
    },
    {
        "id": 30,
        "first_name": "Burtie",
        "last_name": "Kupke",
        "email": "bkupket@cafepress.com",
        "gender": "Polygender"
    },
    {
        "id": 31,
        "first_name": "Alexei",
        "last_name": "Schule",
        "email": "aschuleu@sakura.ne.jp",
        "gender": "Agender"
    },
    {
        "id": 32,
        "first_name": "Temple",
        "last_name": "O'Scanlan",
        "email": "toscanlanv@apple.com",
        "gender": "Genderqueer"
    },
    {
        "id": 33,
        "first_name": "Maureen",
        "last_name": "Tebbitt",
        "email": "mtebbittw@reference.com",
        "gender": "Genderqueer"
    },
    {
        "id": 34,
        "first_name": "Emmerich",
        "last_name": "Whymark",
        "email": "ewhymarkx@epa.gov",
        "gender": "Bigender"
    },
    {
        "id": 35,
        "first_name": "Porty",
        "last_name": "Joseland",
        "email": "pjoselandy@loc.gov",
        "gender": "Polygender"
    },
    {
        "id": 36,
        "first_name": "Ange",
        "last_name": "McCowen",
        "email": "amccowenz@ebay.com",
        "gender": "Non-binary"
    },
    {
        "id": 37,
        "first_name": "Andrew",
        "last_name": "Lyal",
        "email": "alyal10@cam.ac.uk",
        "gender": "Polygender"
    },
    {
        "id": 38,
        "first_name": "Albert",
        "last_name": "Kee",
        "email": "akee11@europa.eu",
        "gender": "Non-binary"
    },
    {
        "id": 39,
        "first_name": "Riki",
        "last_name": "Taffs",
        "email": "rtaffs12@sina.com.cn",
        "gender": "Genderqueer"
    },
    {
        "id": 40,
        "first_name": "Waylen",
        "last_name": "Lethlay",
        "email": "wlethlay13@histats.com",
        "gender": "Male"
    },
    {
        "id": 41,
        "first_name": "Ursala",
        "last_name": "Rawsthorne",
        "email": "urawsthorne14@networkadvertising.org",
        "gender": "Agender"
    },
    {
        "id": 42,
        "first_name": "Ardisj",
        "last_name": "Norrington",
        "email": "anorrington15@ucsd.edu",
        "gender": "Genderqueer"
    },
    {
        "id": 43,
        "first_name": "Ambrose",
        "last_name": "Toffler",
        "email": "atoffler16@purevolume.com",
        "gender": "Male"
    },
    {
        "id": 44,
        "first_name": "Germain",
        "last_name": "Pilmoor",
        "email": "gpilmoor17@jimdo.com",
        "gender": "Male"
    },
    {
        "id": 45,
        "first_name": "Melania",
        "last_name": "Paish",
        "email": "mpaish18@skype.com",
        "gender": "Genderqueer"
    },
    {
        "id": 46,
        "first_name": "Eugenio",
        "last_name": "Petzold",
        "email": "epetzold19@ebay.com",
        "gender": "Genderqueer"
    },
    {
        "id": 47,
        "first_name": "Angela",
        "last_name": "Dominighi",
        "email": "adominighi1a@mayoclinic.com",
        "gender": "Genderqueer"
    },
    {
        "id": 48,
        "first_name": "Peria",
        "last_name": "Labrenz",
        "email": "plabrenz1b@google.ca",
        "gender": "Non-binary"
    },
    {
        "id": 49,
        "first_name": "Ellerey",
        "last_name": "Steven",
        "email": "esteven1c@va.gov",
        "gender": "Polygender"
    },
    {
        "id": 50,
        "first_name": "Anica",
        "last_name": "Pinnere",
        "email": "apinnere1d@networksolutions.com",
        "gender": "Female"
    }
]